yakh/__init__.py
yakh/kafka_handler.py
yakh/kafka_producers.py
yakh-0.0.5.dist-info/LICENSE
yakh-0.0.5.dist-info/METADATA
yakh-0.0.5.dist-info/WHEEL
yakh-0.0.5.dist-info/top_level.txt
yakh-0.0.5.dist-info/RECORD
