Metadata-Version: 2.1
Name: yakh
Version: 0.0.5
Summary: Yet Another Kafka log Handler.
Home-page: https://github.com/jmcdon03/yakh
Author: Jonathan McDonough
Author-email: jonathan.mcdonough@tufts.edu
License: UNKNOWN
Project-URL: Bug Tracker, https://github.com/jmcdon03/yakh/issues
Platform: UNKNOWN
Classifier: Programming Language :: Python :: 3
Classifier: License :: OSI Approved :: MIT License
Classifier: Operating System :: OS Independent
Requires-Python: >=3.7
License-File: LICENSE
Requires-Dist: confluent-kafka
